blend_agents_observability-1.0.5.dist-info/licenses/LICENSE
observability_logger/__init__.py
observability_logger/config/__init__.py
observability_logger/config/logging_config.py
observability_logger/config/settings.py
observability_logger/core/__init__.py
observability_logger/core/emitter.py
observability_logger/core/formatter.py
observability_logger/core/logging_manager.py
observability_logger/core/tracer.py
observability_logger/core/utils.py
observability_logger/models/__init__.py
observability_logger/models/agent_logger.py
observability_logger/models/events.py
observability_logger/models/node.py
blend_agents_observability-1.0.5.dist-info/METADATA
blend_agents_observability-1.0.5.dist-info/WHEEL
blend_agents_observability-1.0.5.dist-info/top_level.txt
blend_agents_observability-1.0.5.dist-info/RECORD
