Metadata-Version: 2.4
Name: blend-agents-observability
Version: 1.0.5
Summary: Observability logger for Blend360 internal agent workflows.
Author-email: Blend Team Latam <pipy.latam@Blend360.com>
License-Expression: GPL-3.0-only
Project-URL: Homepage, https://github.com/ai-scm/AgentObservability
Project-URL: Documentation, https://github.com/ai-scm/AgentObservability
Project-URL: Repository, https://github.com/ai-scm/AgentObservability
Project-URL: Issues, https://github.com/ai-scm/AgentObservability/issues
Keywords: observability,agents,ai,monitoring,tracing,blend360
Classifier: Development Status :: 3 - Alpha
Classifier: Intended Audience :: Developers
Classifier: Programming Language :: Python :: 3
Classifier: Programming Language :: Python :: 3.9
Classifier: Programming Language :: Python :: 3.10
Classifier: Programming Language :: Python :: 3.11
Classifier: Programming Language :: Python :: 3.12
Classifier: Topic :: Software Development :: Libraries :: Python Modules
Classifier: Topic :: System :: Monitoring
Requires-Python: >=3.9
License-File: LICENSE
Requires-Dist: boto3>=1.34.0
Requires-Dist: pydantic>=2.0.0
Provides-Extra: dev
Requires-Dist: pytest>=7.0.0; extra == "dev"
Requires-Dist: pytest-cov>=4.0.0; extra == "dev"
Requires-Dist: pytest-mock>=3.10.0; extra == "dev"
Requires-Dist: hypothesis>=6.0.0; extra == "dev"
Requires-Dist: moto>=5.0.0; extra == "dev"
Requires-Dist: black>=23.0.0; extra == "dev"
Requires-Dist: ruff>=0.1.0; extra == "dev"
Requires-Dist: mypy>=1.0.0; extra == "dev"
Requires-Dist: boto3-stubs[kinesis]>=1.34.0; extra == "dev"
Dynamic: license-file
